{
  "grid_id": "418",
  "rows": [
    {
      "id": "size_under_x",
      "name": "Area less than 100,000 km²",
      "variantId": 4
    },
    {
      "id": "50_plus_skyscrapers",
      "name": "Has 50+ skyscrapers",
      "variantId": null
    },
    {
      "id": "is_monarchy",
      "name": "Is a monarchy",
      "variantId": null
    }
  ],
  "columns": [
    {
      "id": "continent",
      "name": "In Asia",
      "variantId": 0
    },
    {
      "id": "flag_rwb",
      "name": "Flag with only red, white, and blue",
      "variantId": null
    },
    {
      "id": "played_world_cup",
      "name": "Has played in the Men's FIFA World Cup",
      "variantId": null
    }
  ],
  "answers": {
    "match_box_1": [
      "Armenia",
      "Azerbaijan",
      "Bahrain",
      "Bhutan",
      "British Indian Ocean Territory",
      "Brunei",
      "Christmas Island",
      "Cocos Islands",
      "Cyprus",
      "Georgia",
      "Hong Kong",
      "Israel",
      "Jordan",
      "Kuwait",
      "Lebanon",
      "Macau",
      "Maldives",
      "Palestine",
      "Qatar",
      "Singapore",
      "South Korea",
      "Sri Lanka",
      "Taiwan",
      "Timor-Leste",
      "United Arab Emirates"
    ],
    "match_box_2": [
      "Bouvet Island",
      "Caribbean Netherlands",
      "Cook Islands",
      "Costa Rica",
      "Czechia",
      "Faroe Islands",
      "French Southern Territories",
      "Heard Island and McDonald Islands",
      "Luxembourg",
      "Mayotte",
      "Netherlands",
      "Panama",
      "Puerto Rico",
      "Samoa",
      "Slovakia",
      "Svalbard and Jan Mayen",
      "Taiwan",
      "Wallis and Futuna"
    ],
    "match_box_3": [
      "Austria",
      "Belgium",
      "Bosnia and Herzegovina",
      "Costa Rica",
      "Croatia",
      "Czechia",
      "Denmark",
      "El Salvador",
      "Haiti",
      "Hungary",
      "Ireland",
      "Israel",
      "Jamaica",
      "Kuwait",
      "Netherlands",
      "Panama",
      "Portugal",
      "Qatar",
      "Serbia",
      "Slovakia",
      "Slovenia",
      "South Korea",
      "Switzerland",
      "Togo",
      "Trinidad and Tobago",
      "United Arab Emirates"
    ],
    "match_box_4": [
      "Cambodia",
      "China",
      "Hong Kong",
      "India",
      "Indonesia",
      "Japan",
      "Malaysia",
      "Philippines",
      "Qatar",
      "Russia",
      "Saudi Arabia",
      "Singapore",
      "South Korea",
      "Taiwan",
      "Thailand",
      "Türkiye",
      "United Arab Emirates",
      "Vietnam"
    ],
    "match_box_5": [
      "Australia",
      "Panama",
      "Russia",
      "Taiwan",
      "Thailand",
      "United Kingdom",
      "United States of America"
    ],
    "match_box_6": [
      "Australia",
      "Brazil",
      "Canada",
      "China",
      "Indonesia",
      "Japan",
      "Mexico",
      "Panama",
      "Qatar",
      "Russia",
      "Saudi Arabia",
      "South Korea",
      "Türkiye",
      "United Arab Emirates",
      "United Kingdom",
      "United States of America"
    ],
    "match_box_7": [
      "Bahrain",
      "Bhutan",
      "British Indian Ocean Territory",
      "Brunei",
      "Cambodia",
      "Christmas Island",
      "Cocos Islands",
      "Japan",
      "Jordan",
      "Kuwait",
      "Malaysia",
      "Oman",
      "Qatar",
      "Saudi Arabia",
      "Thailand",
      "United Arab Emirates"
    ],
    "match_box_8": [
      "Australia",
      "Bouvet Island",
      "Caribbean Netherlands",
      "Cook Islands",
      "Faroe Islands",
      "Heard Island and McDonald Islands",
      "Luxembourg",
      "Netherlands",
      "New Zealand",
      "Norway",
      "Svalbard and Jan Mayen",
      "Thailand",
      "United Kingdom"
    ],
    "match_box_9": [
      "Australia",
      "Belgium",
      "Canada",
      "Denmark",
      "Jamaica",
      "Japan",
      "Kuwait",
      "Morocco",
      "Netherlands",
      "New Zealand",
      "Norway",
      "Qatar",
      "Saudi Arabia",
      "Spain",
      "Sweden",
      "United Arab Emirates",
      "United Kingdom"
    ]
  }
}