{
  "grid_id": "456",
  "rows": [
    {
      "id": "coastline_length_over_x",
      "name": "Has coastline, with length greater than 2,000 km",
      "variantId": 3
    },
    {
      "id": "borders_x_to_y",
      "name": "Borders 3-4 countries",
      "variantId": 2
    },
    {
      "id": "capital_population_over_x",
      "name": "Capital city population over 1 million",
      "variantId": 4
    }
  ],
  "columns": [
    {
      "id": "co2_emissions_per_capita_over_x",
      "name": "CO₂ emissions per capita over 5 tCO₂/year",
      "variantId": 5
    },
    {
      "id": "is_monarchy",
      "name": "Is a monarchy",
      "variantId": null
    },
    {
      "id": "continent",
      "name": "In Europe",
      "variantId": 1
    }
  ],
  "answers": {
    "match_box_1": [
      "Australia",
      "Canada",
      "China",
      "Estonia",
      "Finland",
      "Germany",
      "Greenland",
      "Iceland",
      "Iran",
      "Ireland",
      "Italy",
      "Japan",
      "Libya",
      "Malaysia",
      "Maldives",
      "New Caledonia",
      "New Zealand",
      "Norway",
      "Oman",
      "Russia",
      "Saudi Arabia",
      "South Africa",
      "South Korea",
      "Taiwan",
      "Türkiye",
      "United Arab Emirates",
      "United States of America"
    ],
    "match_box_2": [
      "Australia",
      "Bahamas",
      "Canada",
      "Denmark",
      "Greenland",
      "Japan",
      "Malaysia",
      "Morocco",
      "New Zealand",
      "Norway",
      "Oman",
      "Papua New Guinea",
      "Saudi Arabia",
      "Solomon Islands",
      "Spain",
      "Svalbard and Jan Mayen",
      "Sweden",
      "Thailand",
      "United Arab Emirates",
      "United Kingdom"
    ],
    "match_box_3": [
      "Åland",
      "Croatia",
      "Denmark",
      "Estonia",
      "Finland",
      "France",
      "Germany",
      "Greece",
      "Iceland",
      "Ireland",
      "Italy",
      "Norway",
      "Portugal",
      "Russia",
      "Spain",
      "Svalbard and Jan Mayen",
      "Sweden",
      "Türkiye",
      "Ukraine",
      "United Kingdom"
    ],
    "match_box_4": [
      "Belgium",
      "Bosnia and Herzegovina",
      "Czechia",
      "Finland",
      "Luxembourg",
      "Malaysia",
      "Norway",
      "Oman",
      "Slovenia",
      "Turkmenistan"
    ],
    "match_box_5": [
      "Belgium",
      "Cambodia",
      "Luxembourg",
      "Malaysia",
      "Morocco",
      "Norway",
      "Oman",
      "Sweden",
      "Thailand"
    ],
    "match_box_6": [
      "Albania",
      "Belgium",
      "Bosnia and Herzegovina",
      "Czechia",
      "Finland",
      "Georgia",
      "Greece",
      "Kosovo",
      "Latvia",
      "Lithuania",
      "Luxembourg",
      "Norway",
      "Slovenia",
      "Sweden"
    ],
    "match_box_7": [
      "Austria",
      "Belarus",
      "Belgium",
      "Bulgaria",
      "Canada",
      "China",
      "Czechia",
      "Germany",
      "Iran",
      "Italy",
      "Japan",
      "Kazakhstan",
      "Kuwait",
      "Libya",
      "Malaysia",
      "Mongolia",
      "Oman",
      "Poland",
      "Qatar",
      "Russia",
      "Saudi Arabia",
      "Serbia",
      "Singapore",
      "South Africa",
      "South Korea",
      "Taiwan",
      "Türkiye",
      "Turkmenistan",
      "United Arab Emirates"
    ],
    "match_box_8": [
      "Belgium",
      "Cambodia",
      "Canada",
      "Denmark",
      "Japan",
      "Jordan",
      "Kuwait",
      "Malaysia",
      "Morocco",
      "Oman",
      "Qatar",
      "Saudi Arabia",
      "Spain",
      "Thailand",
      "United Arab Emirates",
      "United Kingdom"
    ],
    "match_box_9": [
      "Austria",
      "Azerbaijan",
      "Belarus",
      "Belgium",
      "Bulgaria",
      "Czechia",
      "Denmark",
      "France",
      "Georgia",
      "Germany",
      "Hungary",
      "Italy",
      "Kazakhstan",
      "Poland",
      "Romania",
      "Russia",
      "Serbia",
      "Spain",
      "Türkiye",
      "Ukraine",
      "United Kingdom"
    ]
  }
}